{
  "date": "2026-02-16",
  "story": {
    "title": "VOA: Lesson 1: Who Are You?",
    "source_url": "https://learningenglish.voanews.com/a/8108887.html",
    "lines": [
      {
        "en": "No media source currently available"
      },
      {
        "en": "Lesson 1: Who Are You?"
      },
      {
        "en": "What do you think of this lesson?"
      },
      {
        "en": "We want to hear from you."
      },
      {
        "en": "We have a new comment system."
      },
      {
        "en": "Here is how it works:"
      },
      {
        "en": "Each time you return to comment on the Learning English site, you can use your account and see your comments and replies to them."
      }
    ]
  }
}